{
  "meta": {
    "version": "1.0",
    "purpose": "Meta tags and title templates for all pages",
    "maxTitleLength": 60,
    "maxDescriptionLength": 160
  },

  "pages": {
    "home": {
      "title": "AC & Freezer Service สมุทรปราการ | ซ่อม ล้าง ติดตั้ง 24 ชม",
      "description": "บริการซ่อม ล้าง ติดตั้ง แอร์ และตู้แช่แข็ง สมุทรปราการ 24 ชม. ช่างมืออาชีพ เร็ว เชื่อถือได้ พร้อมรับประกัน",
      "keywords": "ซ่อมแอร์ สมุทรปราการ, ล้างแอร์, บริการตู้แช่, ช่างแอร์ใกล้ฉัน",
      "ogTitle": "บริการซ่อม/ล้าง/ติดตั้ง แอร์และตู้แช่ สมุทรปราการ 24ชม",
      "ogDescription": "ช่างมืออาชีพประสบการณ์สูง บริการด่วน 2-4 ชั่วโมง พร้อมรับประกัน",
      "canonical": "https://www.acrfreezer-samutprakan.com/"
    },

    "servicesMain": {
      "title": "บริการ - AC & Freezer Service สมุทรปราการ | ซ่อม ล้าง ติดตั้ง",
      "description": "บริการซ่อมแอร์, ล้างแอร์, บริการตู้แช่แข็ง, ติดตั้ง, ดูแลรักษา ครบครัน ราคาเข้าท่า",
      "keywords": "บริการแอร์, บริการตู้แช่, ซ่อมแอร์, ล้างแอร์, ติดตั้งแอร์",
      "canonical": "https://www.acrfreezer-samutprakan.com/services/"
    },

    "acRepair": {
      "title": "ซ่อมแอร์ สมุทรปราการ | บริการด่วน 2-4 ชั่วโมง 🔧",
      "description": "ซ่อมแอร์ สมุทรปราการ แอร์ไม่เย็น น้ำหยด ติดๆ ดับๆ บริการด่วน เช็คปัญหาฟรี ประกัน 30 วัน",
      "keywords": "ซ่อมแอร์, แอร์ไม่เย็น, เติมน้ำยาแอร์, น้ำหยด, สมุทรปราการ",
      "canonical": "https://www.acrfreezer-samutprakan.com/services/air-conditioner-repair/",
      "schema": "Service"
    },

    "acCleaning": {
      "title": "ล้างแอร์ สมุทรปราการ | ป้องกันเชื้อรา ประหยัดไฟ ✨",
      "description": "ล้างแอร์บ้าน ล้างแอร์โรงงาน สมุทรปราการ ป้องกันเชื้อรา ประหยัดไฟ 20-30% ฟรีตรวจสอบ",
      "keywords": "ล้างแอร์, เชื้อรา, กลิ่นอับ, ประหยัดไฟ, สมุทรปราการ",
      "canonical": "https://www.acrfreezer-samutprakan.com/services/air-conditioner-cleaning/",
      "schema": "Service"
    },

    "freezerService": {
      "title": "บริการตู้แช่ สมุทรปราการ | ซ่อม ล้าง ติดตั้ง 🧊",
      "description": "บริการตู้แช่แข็ง ซ่อม ล้าง ติดตั้ง ห้องเย็น สมุทรปราการ ช่างมืออาชีพ ราคาเข้าท่า",
      "keywords": "บริการตู้แช่, ซ่อมตู้เย็น, ล้างตู้แช่, ติดตั้งตู้เย็น",
      "canonical": "https://www.acrfreezer-samutprakan.com/services/freezer-service/",
      "schema": "Service"
    },

    "contact": {
      "title": "ติดต่อเรา | AC & Freezer Service สมุทรปราการ 📞 24 ชม",
      "description": "ติดต่อ AC & Freezer Service Samut Prakan โทร 089-xxx-xxxx ปฏิบัติการ 24 ชม. นัดหมายออนไลน์",
      "keywords": "ติดต่อ, โทรศัพท์, ที่อยู่, แผนที่, นัดหมาย",
      "canonical": "https://www.acrfreezer-samutprakan.com/contact/",
      "schema": "ContactPage"
    },

    "blogMain": {
      "title": "บล็อก | AC & Freezer Service - เคล็ดลับ ดูแลรักษา บำรุง",
      "description": "บล็อกเรื่องแอร์ ตู้แช่ เคล็ดลับดูแลรักษา บำรุง ประหยัดไฟ ความรู้เกี่ยวกับสินค้า",
      "keywords": "บล็อก, เคล็ดลับ, ดูแลแอร์, บำรุงแอร์, ประหยัดไฟ",
      "canonical": "https://www.acrfreezer-samutprakan.com/blog/"
    },

    "areasMain": {
      "title": "พื้นที่บริการ - สมุทรปราการ ทั้ง 6 อำเภอ",
      "description": "บริการ AC & Freezer ครอบคลุมทั่วสมุทรปราการ บางพลี พระประแดง บางบ่อ บางเสาธง พระสมุทรเจดีย์",
      "keywords": "พื้นที่บริการ, สมุทรปราการ, บางพลี, พระประแดง, บางบ่อ",
      "canonical": "https://www.acrfreezer-samutprakan.com/areas/"
    }
  },

  "socialMediaTemplates": {
    "facebook": {
      "servicePost": {
        "headline": "ซ่อมแอร์ สมุทรปราการ ⭐ บริการด่วน 2-4 ชั่วโมง",
        "description": "แอร์ไม่เย็น? มีปัญหา? เรามาแก้ไขให้คุณ ✅ ช่างมืออาชีพ เชื่อถือได้ ราคายุติธรรม\n\n📞 089-xxx-xxxx\n🕐 24 ชั่วโมง\n🛡️ ประกัน 30 วัน",
        "hashtags": "#ซ่อมแอร์ #สมุทรปราการ #แอร์ไม่เย็น #ช่างแอร์ #บริการด่วน"
      },
      "testimonialPost": {
        "headline": "ลูกค้าพอใจ 5 ดาว ⭐⭐⭐⭐⭐",
        "description": "\"แอร์เย็นสบายตั้งแต่ช่างมา งานดี ราคายุติธรรม ขอแนะนำเพื่อน ๆ\"\n- น.ส. สมหญิง บ้านท่ารวก\n\nขอบคุณที่ไว้ใจ! 😊",
        "hashtags": "#รีวิว #ลูกค้าพอใจ #ซ่อมแอร์ #สมุทรปราการ"
      },
      "blogPost": {
        "headline": "เคล็ดลับล้างแอร์รับหน้าร้อน 🌞",
        "description": "หน้าร้อนแอร์ทำงานหนัก ต้องล้างสม่ำเสมอ เพื่อประหยัดไฟ เย็นสบาย ป้องกันเชื้อรา อ่านเพิ่มเติม →",
        "hashtags": "#บล็อก #หน้าร้อน #เคล็ดลับแอร์ #ประหยัดไฟ"
      }
    },
    "line": {
      "servicePromotion": "🔧 บริการซ่อมแอร์ สมุทรปราการ\nแอร์ไม่เย็น? ลดสิทสต์ตอบ!\n\n📞 ติดต่อเลย: 089-xxx-xxxx\n💰 ฟรีเช็คปัญหา\n✅ ประกัน 30 วัน\n\n#ซ่อมแอร์ #สมุทรปราการ"
    }
  },

  "emailTemplates": {
    "confirmationEmail": {
      "subject": "ยืนยันการนัดหมาย AC & Freezer Service Samut Prakan",
      "preview": "ขอบคุณที่สั่งบริการ ช่างจะติดต่อคุณในเร็ว ๆ นี้"
    },
    "reminderEmail": {
      "subject": "เตือนการนัดหมายซ่อมแอร์ ชั่วโมง x (แบบข้างหน้า)",
      "preview": "ช่างจะมาถึงในอีก 2 ชั่วโมง"
    },
    "reviewEmail": {
      "subject": "รีวิวบริการของเรา 😊 - AC & Freezer Service",
      "preview": "โปรดเขียนรีวิวการบริการของเรา ขอบคุณครับ"
    }
  },

  "adCopyTemplates": {
    "googleSearchAds": {
      "headline1": "ซ่อมแอร์ สมุทรปราการ",
      "headline2": "บริการด่วน 2-4 ชั่วโมง",
      "headline3": "ช่างมืออาชีพ ราคายุติธรรม",
      "description": "แอร์ไม่เย็น น้ำหยด ติดๆ ดับๆ แก้ไขด่วน ฟรีเช็คปัญหา ประกัน 30 วัน"
    },
    "facebookAds": {
      "headline": "ซ่อมแอร์ ล้างแอร์ สมุทรปราการ",
      "description": "แอร์เสีย? ล้างแอร์? ติดตั้ง? เรามาแก้ให้! บริการด่วน ช่างดี ราคาตรง\n\n📞 089-xxx-xxxx"
    }
  }
}
